backports/__init__.py
backports/unittest/__init__.py
backports/unittest/__main__.py
backports/unittest/_colorize.py
backports/unittest/_log.py
backports/unittest/async_case.py
backports/unittest/case.py
backports/unittest/loader.py
backports/unittest/main.py
backports/unittest/mock.py
backports/unittest/result.py
backports/unittest/runner.py
backports/unittest/signals.py
backports/unittest/suite.py
backports/unittest/util.py
backports/unittest/_test/__init__.py
backports/unittest/_test/support/__init__.py
backports/unittest/_test/support/ast_helper.py
backports/unittest/_test/support/asynchat.py
backports/unittest/_test/support/asyncore.py
backports/unittest/_test/support/bytecode_helper.py
backports/unittest/_test/support/channels.py
backports/unittest/_test/support/hashlib_helper.py
backports/unittest/_test/support/hypothesis_helper.py
backports/unittest/_test/support/i18n_helper.py
backports/unittest/_test/support/import_helper.py
backports/unittest/_test/support/logging_helper.py
backports/unittest/_test/support/numbers.py
backports/unittest/_test/support/os_helper.py
backports/unittest/_test/support/pty_helper.py
backports/unittest/_test/support/refleak_helper.py
backports/unittest/_test/support/script_helper.py
backports/unittest/_test/support/smtpd.py
backports/unittest/_test/support/socket_helper.py
backports/unittest/_test/support/strace_helper.py
backports/unittest/_test/support/testcase.py
backports/unittest/_test/support/threading_helper.py
backports/unittest/_test/support/venv.py
backports/unittest/_test/support/warnings_helper.py
backports/unittest/_test/support/_hypothesis_stubs/__init__.py
backports/unittest/_test/support/_hypothesis_stubs/_helpers.py
backports/unittest/_test/support/_hypothesis_stubs/strategies.py
backports_unittest-0.0.1.dist-info/METADATA
backports_unittest-0.0.1.dist-info/WHEEL
backports_unittest-0.0.1.dist-info/top_level.txt
backports_unittest-0.0.1.dist-info/RECORD
