Metadata-Version: 2.4
Name: backports.unittest
Version: 0.0.1
Summary: "Backport of unittest and unittest.mock"
Author: Alex Willmer
Author-email: alex@moreati.org.uk
License: PSF-2.0
Keywords: backports,unittest,mock
Classifier: Development Status :: 3 - Alpha
Classifier: Intended Audience :: Developers
Classifier: Operating System :: OS Independent
Classifier: Programming Language :: Python :: 3 :: Only
Classifier: Programming Language :: Python :: 3.10
Classifier: Programming Language :: Python :: 3.11
Classifier: Programming Language :: Python :: 3.12
Classifier: Programming Language :: Python :: 3.13
Classifier: Programming Language :: Python :: 3.14
Classifier: Programming Language :: Python :: Implementation :: CPython
Classifier: Topic :: Software Development :: Testing
Requires-Python: >=3.10
